odoo/addons/agreement_legal/README.rst
odoo/addons/agreement_legal/__init__.py
odoo/addons/agreement_legal/__manifest__.py
odoo/addons/agreement_legal/data/agreement_stage.xml
odoo/addons/agreement_legal/data/agreement_type.xml
odoo/addons/agreement_legal/data/cron.xml
odoo/addons/agreement_legal/data/ir_sequence.xml
odoo/addons/agreement_legal/demo/demo.xml
odoo/addons/agreement_legal/i18n/agreement_legal.pot
odoo/addons/agreement_legal/i18n/es.po
odoo/addons/agreement_legal/i18n/es_AR.po
odoo/addons/agreement_legal/i18n/fr.po
odoo/addons/agreement_legal/i18n/it.po
odoo/addons/agreement_legal/i18n/pt.po
odoo/addons/agreement_legal/i18n/pt_BR.po
odoo/addons/agreement_legal/i18n/pt_PT.po
odoo/addons/agreement_legal/i18n/sv.po
odoo/addons/agreement_legal/i18n/zh_CN.po
odoo/addons/agreement_legal/models/__init__.py
odoo/addons/agreement_legal/models/agreement.py
odoo/addons/agreement_legal/models/agreement_appendix.py
odoo/addons/agreement_legal/models/agreement_clause.py
odoo/addons/agreement_legal/models/agreement_line.py
odoo/addons/agreement_legal/models/agreement_recital.py
odoo/addons/agreement_legal/models/agreement_section.py
odoo/addons/agreement_legal/models/agreement_stage.py
odoo/addons/agreement_legal/models/agreement_subtype.py
odoo/addons/agreement_legal/models/agreement_type.py
odoo/addons/agreement_legal/models/res_config_settings.py
odoo/addons/agreement_legal/readme/CONFIGURE.md
odoo/addons/agreement_legal/readme/CONTRIBUTORS.md
odoo/addons/agreement_legal/readme/CREDITS.md
odoo/addons/agreement_legal/readme/DESCRIPTION.md
odoo/addons/agreement_legal/readme/ROADMAP.md
odoo/addons/agreement_legal/readme/USAGE.md
odoo/addons/agreement_legal/report/agreement.xml
odoo/addons/agreement_legal/security/ir.model.access.csv
odoo/addons/agreement_legal/security/res_groups.xml
odoo/addons/agreement_legal/static/description/icon.png
odoo/addons/agreement_legal/static/description/index.html
odoo/addons/agreement_legal/static/src/js/form_view.esm.js
odoo_addon_agreement_legal-18.0.1.0.2.6.dist-info/METADATA
odoo_addon_agreement_legal-18.0.1.0.2.6.dist-info/WHEEL
odoo_addon_agreement_legal-18.0.1.0.2.6.dist-info/top_level.txt
odoo_addon_agreement_legal-18.0.1.0.2.6.dist-info/RECORD
